deepluq/__init__.py
deepluq/metrics_dl.py
deepluq/metrics_vla.py
deepluq/utils.py
deepluq/version.py
deepluq-0.1.2.dist-info/LICENSE
deepluq-0.1.2.dist-info/METADATA
deepluq-0.1.2.dist-info/WHEEL
deepluq-0.1.2.dist-info/entry_points.txt
deepluq-0.1.2.dist-info/top_level.txt
deepluq-0.1.2.dist-info/RECORD
