Metadata-Version: 2.1
Name: deepluq
Version: 0.1.2
Summary: Package to quantify uncertainty in deep learning models
Author-email: Chengjie Lu <chengjielu@simula.no>
Maintainer-email: Chengjie Lu <chengjielu@simula.no>
License: --- Start of Definition of INTO-CPS Association Public License ---
Project-URL: homepage, https://github.com/chengjie-lu/deepluq
Project-URL: documentation, https://github.com/chengjie-lu/deepluq
Project-URL: repository, https://github.com/chengjie-lu/deepluq
Keywords: deep learning,uncertainty quantification,machine learning
Classifier: Development Status :: 3 - Alpha
Classifier: Intended Audience :: Developers
Classifier: Topic :: Software Development :: Build Tools
Classifier: Programming Language :: Python :: 3
Classifier: Programming Language :: Python :: 3.8
Classifier: Programming Language :: Python :: 3.9
Classifier: Programming Language :: Python :: 3.10
Classifier: Programming Language :: Python :: 3.11
Classifier: Programming Language :: Python :: 3.12
Requires-Python: >=3.8
License-File: LICENSE
Requires-Dist: aiohttp
Requires-Dist: hdbscan
Requires-Dist: ImageHash
Requires-Dist: matplotlib
Requires-Dist: numpy
Requires-Dist: onnx
Requires-Dist: onnxruntime
Requires-Dist: opencv-python
Requires-Dist: pandas
Requires-Dist: pillow
Requires-Dist: psutil
Requires-Dist: pycocotools
Requires-Dist: pypylon
Requires-Dist: requests
Requires-Dist: scikit-learn
Requires-Dist: scipy
Requires-Dist: torch
Requires-Dist: torchmetrics
Requires-Dist: torchvision
Requires-Dist: tqdm
Provides-Extra: dev
Requires-Dist: jupyter-book; extra == "dev"
Requires-Dist: pre-commit; extra == "dev"
Requires-Dist: pydot; extra == "dev"
Requires-Dist: sphinx-autoapi; extra == "dev"
Requires-Dist: tox; extra == "dev"
Provides-Extra: test
Requires-Dist: coverage; extra == "test"
Requires-Dist: pytest; extra == "test"
Requires-Dist: pytest-cov; extra == "test"
Requires-Dist: pydot; extra == "test"
